pyargus/__init__.py
pyargus/antennaArrayPattern.py
pyargus/beamform.py
pyargus/directionEstimation.py
pyargus/tests/DOAEstimationTest.py
pyargus/tests/__init__.py
pyargus/tests/beamformTest.py
pyargus/tests/patternPlotTest.py
pyargus-1.1.post1.dist-info/METADATA
pyargus-1.1.post1.dist-info/WHEEL
pyargus-1.1.post1.dist-info/top_level.txt
pyargus-1.1.post1.dist-info/RECORD
