Metadata-Version: 2.1
Name: pyargus
Version: 1.1.post1
Summary: Signal processing algorithms for antenna arrays
Home-page: https://github.com/petotamas/pyArgus
Author: Tamas Peto
Author-email: petotax@gmail.com
License: UNKNOWN
Platform: UNKNOWN
Classifier: Programming Language :: Python :: 3
Classifier: License :: OSI Approved :: GNU General Public License v3 (GPLv3)
Classifier: Operating System :: OS Independent
Classifier: Programming Language :: Python :: 3
Classifier: Topic :: Scientific/Engineering
